{"Equipment":{"context":"Equipment","items":{"Survival Gear":{"name":"Survival Gear","items":{"Filtration Canteen Filter":{"Equipment":{"Item":{"name":"Filtration Canteen Filter","notes":"100 quarts","cost":25.0,"weight":1.0,"skill":null,"mod_groups":[]}}},"Pocket MultiTool":{"Equipment":{"Item":{"name":"Pocket MultiTool","notes":null,"cost":50.0,"weight":0.5,"skill":null,"mod_groups":[]}}},"Smoke Marker":{"Equipment":{"Item":{"name":"Smoke Marker","notes":null,"cost":8.0,"weight":0.1,"skill":null,"mod_groups":[]}}},"Dome Tent (8 man)":{"Equipment":{"Armor":{"name":"Dome Tent (8 man)","dr":{"All":2},"pd":null,"cover":[],"cost":250.0,"weight":20.0,"mod_groups":[],"skill":null,"stats_affected":[],"skills_affected":[],"container":null,"_extra":[]}}},"Survival Knife":{"Equipment":{"Weapon":{"Melee":{"name":"Survival Knife","damage":[{"Cut":{"Sw":-2}},{"Imp":{"Thr":0}}],"max_damage":null,"cost":100.0,"weight":1.5,"skill":"Knife","notes":null,"mod_groups":[],"acc":null,"st_req":null}}}},"Dome Tent (2 man)":{"Equipment":{"Armor":{"name":"Dome Tent (2 man)","dr":{"All":1},"pd":null,"cover":[],"cost":100.0,"weight":7.0,"mod_groups":[],"skill":null,"stats_affected":[],"skills_affected":[],"container":null,"_extra":[]}}},"Filter Pump":{"Equipment":{"Item":{"name":"Filter Pump","notes":"100 quarts","cost":80.0,"weight":1.0,"skill":null,"mod_groups":[]}}},"Sleeping Bag":{"Equipment":{"Item":{"name":"Sleeping Bag","notes":null,"cost":75.0,"weight":6.0,"skill":null,"mod_groups":[]}}},"Global Positioning System Unit":{"Equipment":{"Item":{"name":"Global Positioning System Unit","notes":null,"cost":200.0,"weight":2.0,"skill":null,"mod_groups":[]}}},"Adventure Watch":{"Equipment":{"Item":{"name":"Adventure Watch","notes":"alti/depth/temp/compass","cost":100.0,"weight":null,"skill":"0.2","mod_groups":[]}}},"Emergency Tent (1 man)":{"Equipment":{"Armor":{"name":"Emergency Tent (1 man)","dr":{"All":1},"pd":null,"cover":[],"cost":50.0,"weight":3.0,"mod_groups":[],"skill":null,"stats_affected":[],"skills_affected":[],"container":null,"_extra":[]}}},"Aerial Flare":{"Equipment":{"Item":{"name":"Aerial Flare","notes":null,"cost":8.0,"weight":0.1,"skill":null,"mod_groups":[]}}},"Sleeping Bag Heating Unit":{"Equipment":{"Item":{"name":"Sleeping Bag Heating Unit","notes":null,"cost":50.0,"weight":1.0,"skill":null,"mod_groups":[]}}},"Thermal Suit":{"Equipment":{"Armor":{"name":"Thermal Suit","dr":{"All":1},"pd":{"All":0},"cover":[18,3,4,6],"cost":150.0,"weight":5.0,"mod_groups":[],"skill":null,"stats_affected":[],"skills_affected":[["vs.freezing)",2]],"container":null,"_extra":[]}}},"Canteen":{"Equipment":{"Item":{"name":"Canteen","notes":"1 quart plus cup and cover","cost":10.0,"weight":2.5,"skill":null,"mod_groups":[]}}},"Concentrated Rations":{"Equipment":{"Item":{"name":"Concentrated Rations","notes":"1 weeks food","cost":50.0,"weight":2.0,"skill":null,"mod_groups":[]}}},"Magnetic Compass":{"Equipment":{"Item":{"name":"Magnetic Compass","notes":null,"cost":5.0,"weight":0.0,"skill":null,"mod_groups":[]}}},"Filtration Canteen":{"Equipment":{"Item":{"name":"Filtration Canteen","notes":"1 quart","cost":175.0,"weight":2.5,"skill":null,"mod_groups":[]}}}}},"Armor":{"name":"Armor","items":{"Level IIa Vest":{"Equipment":{"Armor":{"name":"Level IIa Vest","dr":{"All":10},"pd":{"All":2},"cover":[17,9,10,18],"cost":200.0,"weight":1.5,"mod_groups":[],"skill":null,"stats_affected":[],"skills_affected":[],"container":null,"_extra":[]}}},"Nomex Suit":{"Equipment":{"Armor":{"name":"Nomex Suit","dr":{"All":8},"pd":{"All":0},"cover":[4,6,18,3],"cost":250.0,"weight":2.0,"mod_groups":[],"skill":null,"stats_affected":[],"skills_affected":[],"container":null,"_extra":[]}}},"Level IIIa Vest":{"Equipment":{"Armor":{"name":"Level IIIa Vest","dr":{"All":14},"pd":{"All":2},"cover":[9,10,18,17],"cost":350.0,"weight":2.5,"mod_groups":[],"skill":null,"stats_affected":[],"skills_affected":[],"container":null,"_extra":[]}}},"Delta Force Helmet":{"Equipment":{"Armor":{"name":"Delta Force Helmet","dr":{"All":10},"pd":{"All":4},"cover":[4,3],"cost":250.0,"weight":3.0,"mod_groups":[],"skill":null,"stats_affected":[],"skills_affected":[],"container":null,"_extra":[]}}},"Lexan Visor":{"Equipment":{"Armor":{"name":"Lexan Visor","dr":{"All":4},"pd":{"All":2},"cover":[5],"cost":40.0,"weight":0.5,"mod_groups":[],"skill":null,"stats_affected":[],"skills_affected":[],"container":null,"_extra":[]}}},"Light Body Armor (TL7)":{"Equipment":{"Armor":{"name":"Light Body Armor (TL7)","dr":{"All":10},"pd":{"All":2},"cover":[3,4,18,6],"cost":1250.0,"weight":20.0,"mod_groups":[],"skill":null,"stats_affected":[],"skills_affected":[["to DX skills",-1]],"container":null,"_extra":[]}}},"Leather Jacket":{"Equipment":{"Armor":{"name":"Leather Jacket","dr":{"All":1},"pd":{"All":1},"cover":[8,6,17,18,9,11],"cost":250.0,"weight":4.0,"mod_groups":[],"skill":null,"stats_affected":[],"skills_affected":[],"container":null,"_extra":[]}}},"Riot Helmet":{"Equipment":{"Armor":{"name":"Riot Helmet","dr":{"All":5},"pd":{"All":4},"cover":[4,3],"cost":150.0,"weight":3.0,"mod_groups":[],"skill":null,"stats_affected":[],"skills_affected":[],"container":null,"_extra":[]}}},"Composite Vest Inserts":{"Equipment":{"Armor":{"name":"Composite Vest Inserts","dr":{"All":19},"pd":{"All":2},"cover":[17,18,9,11],"cost":500.0,"weight":19.0,"mod_groups":[],"skill":null,"stats_affected":[],"skills_affected":[],"container":null,"_extra":[]}}},"Leather Pants":{"Equipment":{"Armor":{"name":"Leather Pants","dr":{"All":1},"pd":{"All":1},"cover":[11,14],"cost":180.0,"weight":4.0,"mod_groups":[],"skill":null,"stats_affected":[],"skills_affected":[],"container":null,"_extra":[]}}},"Trauma Plate":{"Equipment":{"Armor":{"name":"Trauma Plate","dr":{"All":9},"pd":{"All":0},"cover":[18,17],"cost":85.0,"weight":1.0,"mod_groups":[],"skill":null,"stats_affected":[],"skills_affected":[],"container":null,"_extra":[]}}},"Heavy Assault Vest":{"Equipment":{"Armor":{"name":"Heavy Assault Vest","dr":{"All":16},"pd":{"All":2},"cover":[18,11,17,9],"cost":600.0,"weight":6.0,"mod_groups":[],"skill":null,"stats_affected":[],"skills_affected":[],"container":null,"_extra":[]}}},"Kevlar Glove Liners":{"Equipment":{"Armor":{"name":"Kevlar Glove Liners","dr":{"All":4},"pd":{"All":0},"cover":[7],"cost":10.0,"weight":0.1,"mod_groups":[],"skill":null,"stats_affected":[],"skills_affected":[],"container":null,"_extra":[]}}}}},"Clothing":{"name":"Clothing","items":{"Uniform: Standard Military":{"Equipment":{"Item":{"name":"Uniform: Standard Military","notes":null,"cost":40.0,"weight":1.0,"skill":null,"mod_groups":[]}}},"Belt":{"Equipment":{"Item":{"name":"Belt","notes":null,"cost":2.0,"weight":0.1,"skill":null,"mod_groups":[]}}},"Leather Belt":{"Equipment":{"Item":{"name":"Leather Belt","notes":null,"cost":5.0,"weight":0.2,"skill":null,"mod_groups":[]}}},"Uniform: Combat":{"Equipment":{"Armor":{"name":"Uniform: Combat","dr":{"All":1},"pd":{"All":0},"cover":[17,14,8,18,6],"cost":30.0,"weight":1.5,"mod_groups":[],"skill":null,"stats_affected":[],"skills_affected":[],"container":null,"_extra":[]}}},"Uniform: Winter":{"Equipment":{"Armor":{"name":"Uniform: Winter","dr":{"All":2},"pd":{"All":0},"cover":[6,8,14,17,18],"cost":50.0,"weight":1.0,"mod_groups":[],"skill":null,"stats_affected":[],"skills_affected":[],"container":null,"_extra":[]}}},"Uniform: Parade":{"Equipment":{"Item":{"name":"Uniform: Parade","notes":null,"cost":50.0,"weight":1.0,"skill":null,"mod_groups":[]}}},"Boots":{"Equipment":{"Item":{"name":"Boots","notes":null,"cost":10.0,"weight":1.0,"skill":null,"mod_groups":[]}}},"Boots: heavy leather":{"Equipment":{"Armor":{"name":"Boots: heavy leather","dr":{"All":2},"pd":{"All":2},"cover":[15,16],"cost":30.0,"weight":2.0,"mod_groups":[],"skill":null,"stats_affected":[],"skills_affected":[],"container":null,"_extra":[]}}},"Jeans":{"Equipment":{"Item":{"name":"Jeans","notes":null,"cost":30.0,"weight":0.5,"skill":null,"mod_groups":[]}}},"Civilian clothes":{"Equipment":{"Item":{"name":"Civilian clothes","notes":"Typical civilian clothes","cost":50.0,"weight":1.5,"skill":null,"mod_groups":[]}}},"T-shirt: special figure":{"Equipment":{"Item":{"name":"T-shirt: special figure","notes":null,"cost":7.0,"weight":0.1,"skill":null,"mod_groups":[]}}},"Uniform: Jungle Survival ":{"Equipment":{"Item":{"name":"Uniform: Jungle Survival ","notes":null,"cost":20.0,"weight":1.0,"skill":null,"mod_groups":[]}}},"T-shirt":{"Equipment":{"Item":{"name":"T-shirt","notes":null,"cost":5.0,"weight":0.1,"skill":null,"mod_groups":[]}}}}},"Weapons: Submachine Guns":{"name":"Weapons: Submachine Guns","items":{"Jati Matic 9x19mm":{"Equipment":{"Weapon":{"Ranged":{"name":"Jati Matic 9x19mm","damage":[{"Cr":{"Dice":[3,-1]}}],"max_damage":null,"acc":7,"ss":9,"rof":{"FullAuto":12},"rcl":-1,"min_range":null,"half_dmg_range":null,"max_range":null,"st_req":null,"tripod":false,"cost":400.0,"weight":5.0,"skill":null,"notes":null,"shots":{"Magazine":40},"mod_groups":[],"rl_year":null,"rl_country":"FI","tl":7,"lc":null}}}},"MAC 11. 9x19mm":{"Equipment":{"Weapon":{"Ranged":{"name":"MAC 11. 9x19mm","damage":[{"Cr":{"Dice":[3,-1]}}],"max_damage":null,"acc":6,"ss":9,"rof":{"FullAuto":16},"rcl":-3,"min_range":null,"half_dmg_range":null,"max_range":null,"st_req":null,"tripod":false,"cost":500.0,"weight":7.0,"skill":null,"notes":null,"shots":{"Magazine":20},"mod_groups":[],"rl_year":null,"rl_country":"US","tl":7,"lc":null}}}},"Micro-Uzi 9x19mm":{"Equipment":{"Weapon":{"Ranged":{"name":"Micro-Uzi 9x19mm","damage":[{"Cr":{"Dice":[3,-1]}}],"max_damage":null,"acc":7,"ss":10,"rof":{"FullAuto":20},"rcl":-5,"min_range":null,"half_dmg_range":null,"max_range":null,"st_req":null,"tripod":false,"cost":150.0,"weight":4.0,"skill":null,"notes":null,"shots":{"Magazine":32},"mod_groups":[],"rl_year":null,"rl_country":"IS","tl":7,"lc":null}}}},"H&K MP5S 9x19mm":{"Equipment":{"Weapon":{"Ranged":{"name":"H&K MP5S 9x19mm","damage":[{"Cr":{"Dice":[2,1]}}],"max_damage":null,"acc":8,"ss":10,"rof":{"FullAuto":10},"rcl":-1,"min_range":null,"half_dmg_range":null,"max_range":null,"st_req":null,"tripod":false,"cost":400.0,"weight":7.25,"skill":null,"notes":null,"shots":{"Magazine":30},"mod_groups":[],"rl_year":null,"rl_country":"GR","tl":7,"lc":null}}}},"Mini-Uzi 9x19mm":{"Equipment":{"Weapon":{"Ranged":{"name":"Mini-Uzi 9x19mm","damage":[{"Cr":{"Dice":[3,-1]}}],"max_damage":null,"acc":7,"ss":10,"rof":{"FullAuto":16},"rcl":-3,"min_range":null,"half_dmg_range":null,"max_range":null,"st_req":null,"tripod":false,"cost":150.0,"weight":6.0,"skill":null,"notes":null,"shots":{"Magazine":32},"mod_groups":[],"rl_year":null,"rl_country":"IS","tl":7,"lc":null}}}},"MAC 10. 45. ACP":{"Equipment":{"Weapon":{"Ranged":{"name":"MAC 10. 45. ACP","damage":[{"Cr":{"Dice":[2,1]}}],"max_damage":null,"acc":6,"ss":9,"rof":{"FullAuto":12},"rcl":-2,"min_range":null,"half_dmg_range":null,"max_range":null,"st_req":null,"tripod":false,"cost":500.0,"weight":8.0,"skill":null,"notes":null,"shots":{"Magazine":20},"mod_groups":[],"rl_year":null,"rl_country":"US","tl":7,"lc":null}}}},"Viking 9x19mm":{"Equipment":{"Weapon":{"Ranged":{"name":"Viking 9x19mm","damage":[{"Cr":{"Dice":[3,-1]}}],"max_damage":null,"acc":6,"ss":9,"rof":{"FullAuto":14},"rcl":-3,"min_range":null,"half_dmg_range":null,"max_range":null,"st_req":null,"tripod":false,"cost":400.0,"weight":7.3,"skill":null,"notes":null,"shots":{"Magazine":36},"mod_groups":[],"rl_year":null,"rl_country":"INT","tl":7,"lc":null}}}},"Spectre M-4 9x19mm":{"Equipment":{"Weapon":{"Ranged":{"name":"Spectre M-4 9x19mm","damage":[{"Cr":{"Dice":[3,-1]}}],"max_damage":null,"acc":8,"ss":10,"rof":{"FullAuto":12},"rcl":-1,"min_range":null,"half_dmg_range":null,"max_range":null,"st_req":null,"tripod":false,"cost":450.0,"weight":8.3,"skill":null,"notes":null,"shots":{"Magazine":50},"mod_groups":[],"rl_year":null,"rl_country":"INT","tl":7,"lc":null}}}},"Uzi 9x19mm":{"Equipment":{"Weapon":{"Ranged":{"name":"Uzi 9x19mm","damage":[{"Cr":{"Dice":[3,-1]}}],"max_damage":null,"acc":7,"ss":10,"rof":{"FullAuto":10},"rcl":-1,"min_range":null,"half_dmg_range":null,"max_range":null,"st_req":null,"tripod":false,"cost":150.0,"weight":9.5,"skill":null,"notes":null,"shots":{"Magazine":32},"mod_groups":[],"rl_year":null,"rl_country":"IS","tl":7,"lc":null}}}},"H&K MP5K 9x19mm":{"Equipment":{"Weapon":{"Ranged":{"name":"H&K MP5K 9x19mm","damage":[{"Cr":{"Dice":[2,2]}}],"max_damage":null,"acc":6,"ss":10,"rof":{"FullAuto":10},"rcl":-3,"min_range":null,"half_dmg_range":null,"max_range":null,"st_req":null,"tripod":false,"cost":300.0,"weight":5.0,"skill":null,"notes":null,"shots":{"Magazine":15},"mod_groups":[],"rl_year":null,"rl_country":"GR","tl":7,"lc":null}}}},"H&K MP5 9x19mm":{"Equipment":{"Weapon":{"Ranged":{"name":"H&K MP5 9x19mm","damage":[{"Cr":{"Dice":[3,-1]}}],"max_damage":null,"acc":8,"ss":10,"rof":{"FullAuto":10},"rcl":-1,"min_range":null,"half_dmg_range":null,"max_range":null,"st_req":null,"tripod":false,"cost":340.0,"weight":7.25,"skill":null,"notes":null,"shots":{"Magazine":30},"mod_groups":[],"rl_year":null,"rl_country":"GR","tl":7,"lc":null}}}}}},"Weapons: Automatic pistols":{"name":"Weapons: Automatic pistols","items":{"Glock 22 .40S&W":{"Equipment":{"Weapon":{"Ranged":{"name":"Glock 22 .40S&W","damage":[{"Cr":{"Flat":2}}],"max_damage":null,"acc":3,"ss":null,"rof":{"SemiAuto":3},"rcl":-1,"min_range":null,"half_dmg_range":null,"max_range":null,"st_req":9,"tripod":false,"cost":720.0,"weight":2.0,"skill":"Guns: Pistol","notes":null,"shots":{"MagazinePlus":[15,1]},"mod_groups":[],"rl_year":null,"rl_country":null,"tl":null,"lc":null}}}},"IMI Eagle .357M":{"Equipment":{"Weapon":{"Ranged":{"name":"IMI Eagle .357M","damage":[{"Cr":{"Dice":[3,-1]}}],"max_damage":null,"acc":3,"ss":null,"rof":{"SemiAuto":3},"rcl":-2,"min_range":null,"half_dmg_range":null,"max_range":null,"st_req":10,"tripod":false,"cost":650.0,"weight":4.5,"skill":"Guns: Pistol","notes":null,"shots":{"MagazinePlus":[9,1]},"mod_groups":[],"rl_year":null,"rl_country":null,"tl":null,"lc":null}}}},"AMT Backup 9mmS":{"Equipment":{"Weapon":{"Ranged":{"name":"AMT Backup 9mmS","damage":[{"Cr":{"Dice":[2,0]}}],"max_damage":null,"acc":0,"ss":null,"rof":{"SemiAuto":3},"rcl":-1,"min_range":null,"half_dmg_range":null,"max_range":null,"st_req":8,"tripod":false,"cost":180.0,"weight":1.0,"skill":"Guns: Pistol","notes":null,"shots":{"MagazinePlus":[5,1]},"mod_groups":[],"rl_year":null,"rl_country":null,"tl":null,"lc":null}}}},"Glock 23 .40S&W":{"Equipment":{"Weapon":{"Ranged":{"name":"Glock 23 .40S&W","damage":[{"Cr":{"Flat":2}}],"max_damage":null,"acc":3,"ss":null,"rof":{"SemiAuto":3},"rcl":-1,"min_range":null,"half_dmg_range":null,"max_range":null,"st_req":9,"tripod":false,"cost":665.0,"weight":1.75,"skill":"Guns: Pistol","notes":null,"shots":{"MagazinePlus":[13,1]},"mod_groups":[],"rl_year":null,"rl_country":null,"tl":null,"lc":null}}}},"Glock 20 10mm":{"Equipment":{"Weapon":{"Ranged":{"name":"Glock 20 10mm","damage":[{"Cr":{"DiceMul":[3,-2,1.5]}}],"max_damage":null,"acc":3,"ss":null,"rof":{"SemiAuto":3},"rcl":-2,"min_range":null,"half_dmg_range":null,"max_range":null,"st_req":10,"tripod":false,"cost":750.0,"weight":2.0,"skill":"Guns: Pistol","notes":null,"shots":{"MagazinePlus":[15,1]},"mod_groups":[],"rl_year":null,"rl_country":null,"tl":null,"lc":null}}}},"IMI Eagle .44M":{"Equipment":{"Weapon":{"Ranged":{"name":"IMI Eagle .44M","damage":[{"Cr":{"Flat":3}}],"max_damage":null,"acc":3,"ss":null,"rof":{"SemiAuto":3},"rcl":-3,"min_range":null,"half_dmg_range":null,"max_range":null,"st_req":12,"tripod":false,"cost":750.0,"weight":4.5,"skill":"Guns: Pistol","notes":null,"shots":{"MagazinePlus":[9,1]},"mod_groups":[],"rl_year":null,"rl_country":null,"tl":null,"lc":null}}}},"Beretta 92 9mmP":{"Equipment":{"Weapon":{"Ranged":{"name":"Beretta 92 9mmP","damage":[{"Cr":{"Dice":[2,2]}}],"max_damage":null,"acc":3,"ss":null,"rof":{"SemiAuto":3},"rcl":-1,"min_range":null,"half_dmg_range":null,"max_range":null,"st_req":9,"tripod":false,"cost":400.0,"weight":2.5,"skill":"Guns: Pistol","notes":null,"shots":{"MagazinePlus":[15,1]},"mod_groups":[],"rl_year":null,"rl_country":null,"tl":null,"lc":null}}}},"IMI Eagle .50AE":{"Equipment":{"Weapon":{"Ranged":{"name":"IMI Eagle .50AE","damage":[{"Cr":{"DiceMul":[3,2,1.5]}}],"max_damage":null,"acc":3,"ss":null,"rof":{"SemiAuto":3},"rcl":-4,"min_range":null,"half_dmg_range":null,"max_range":null,"st_req":13,"tripod":false,"cost":1000.0,"weight":4.5,"skill":"Guns: Pistol","notes":null,"shots":{"MagazinePlus":[9,1]},"mod_groups":[],"rl_year":null,"rl_country":null,"tl":null,"lc":null}}}},"Glock 21 .45ACP":{"Equipment":{"Weapon":{"Ranged":{"name":"Glock 21 .45ACP","damage":[{"Cr":{"Flat":2}}],"max_damage":null,"acc":3,"ss":null,"rof":{"SemiAuto":3},"rcl":-2,"min_range":null,"half_dmg_range":null,"max_range":null,"st_req":9,"tripod":false,"cost":720.0,"weight":2.0,"skill":"Guns: Pistol","notes":null,"shots":{"MagazinePlus":[12,1]},"mod_groups":[],"rl_year":null,"rl_country":null,"tl":null,"lc":null}}}},"Glock 17 9mmP":{"Equipment":{"Weapon":{"Ranged":{"name":"Glock 17 9mmP","damage":[{"Cr":{"Dice":[2,2]}}],"max_damage":null,"acc":3,"ss":null,"rof":{"SemiAuto":3},"rcl":-1,"min_range":null,"half_dmg_range":null,"max_range":null,"st_req":9,"tripod":false,"cost":450.0,"weight":2.0,"skill":"Guns: Pistol","notes":null,"shots":{"MagazinePlus":[17,1]},"mod_groups":[],"rl_year":null,"rl_country":null,"tl":null,"lc":null}}}},"Glock 19 9mmP":{"Equipment":{"Weapon":{"Ranged":{"name":"Glock 19 9mmP","damage":[{"Cr":{"Dice":[2,2]}}],"max_damage":null,"acc":3,"ss":null,"rof":{"SemiAuto":3},"rcl":-1,"min_range":null,"half_dmg_range":null,"max_range":null,"st_req":9,"tripod":false,"cost":420.0,"weight":1.75,"skill":"Guns: Pistol","notes":null,"shots":{"MagazinePlus":[15,1]},"mod_groups":[],"rl_year":null,"rl_country":null,"tl":null,"lc":null}}}}}},"Weapons: Revolvers (pistols)":{"name":"Weapons: Revolvers (pistols)","items":{"S&W M610 10mm":{"Equipment":{"Weapon":{"Ranged":{"name":"S&W M610 10mm","damage":[{"Cr":{"DiceMul":[3,-2,1.5]}}],"max_damage":null,"acc":3,"ss":null,"rof":{"SemiAuto":3},"rcl":-3,"min_range":null,"half_dmg_range":null,"max_range":null,"st_req":10,"tripod":false,"cost":550.0,"weight":3.0,"skill":"Guns: Pistol","notes":null,"shots":{"Magazine":6},"mod_groups":[],"rl_year":null,"rl_country":null,"tl":null,"lc":null}}}},"Charter Arms Undercover .38Sp":{"Equipment":{"Weapon":{"Ranged":{"name":"Charter Arms Undercover .38Sp","damage":[{"Cr":{"Dice":[2,-1]}}],"max_damage":null,"acc":2,"ss":null,"rof":{"SemiAuto":3},"rcl":-1,"min_range":null,"half_dmg_range":null,"max_range":null,"st_req":8,"tripod":false,"cost":145.0,"weight":1.5,"skill":"Guns: Pistol","notes":null,"shots":{"Magazine":6},"mod_groups":[],"rl_year":null,"rl_country":null,"tl":null,"lc":null}}}},"S&W M29 .44M":{"Equipment":{"Weapon":{"Ranged":{"name":"S&W M29 .44M","damage":[{"Cr":{"Flat":3}}],"max_damage":null,"acc":2,"ss":null,"rof":{"SemiAuto":3},"rcl":-3,"min_range":null,"half_dmg_range":null,"max_range":null,"st_req":11,"tripod":false,"cost":400.0,"weight":3.25,"skill":"Guns: Pistol","notes":null,"shots":{"Magazine":6},"mod_groups":[],"rl_year":null,"rl_country":null,"tl":null,"lc":null}}}},"Colt Python .357M":{"Equipment":{"Weapon":{"Ranged":{"name":"Colt Python .357M","damage":[{"Cr":{"Dice":[3,-1]}}],"max_damage":null,"acc":3,"ss":null,"rof":{"SemiAuto":3},"rcl":-2,"min_range":null,"half_dmg_range":null,"max_range":null,"st_req":10,"tripod":false,"cost":400.0,"weight":3.0,"skill":"Guns: Pistol","notes":null,"shots":{"Magazine":6},"mod_groups":[],"rl_year":null,"rl_country":null,"tl":null,"lc":null}}}}}},"Communications Equipment":{"name":"Communications Equipment","items":{"Tactical Headset":{"Equipment":{"Item":{"name":"Tactical Headset","notes":"This small headset comes with an communicator with a range of 1/2 mile","cost":400.0,"weight":2.0,"skill":null,"mod_groups":[]}}},"Laser Communicator":{"Equipment":{"Item":{"name":"Laser Communicator","notes":"Must have a clear line-of-sight to target, Cannot be jammed or intercepted","cost":1000.0,"weight":2.0,"skill":null,"mod_groups":[]}}},"Scrambler":{"Equipment":{"Item":{"name":"Scrambler","notes":null,"cost":500.0,"weight":2.0,"skill":null,"mod_groups":[]}}}}},"Vehicles":{"name":"Vehicles","items":{"Pontoon Boat (Miniature)":{"Equipment":{"Item":{"name":"Pontoon Boat (Miniature)","notes":"Carries two people and 550 lbs of gear it has an out-board motor that allows speed up to 10 kts","cost":600.0,"weight":125.0,"skill":null,"mod_groups":[]}}},"Inflatable Raft":{"Equipment":{"Item":{"name":"Inflatable Raft","notes":null,"cost":4500.0,"weight":200.0,"skill":null,"mod_groups":[]}}}}},"Money (TL7)":{"name":"Money (TL7)","items":{"100$":{"Equipment":{"Item":{"name":"100$","notes":"Cash","cost":100.0,"weight":0.01,"skill":null,"mod_groups":[]}}},"10k$ on Account":{"Equipment":{"Item":{"name":"10k$ on Account","notes":null,"cost":10000.0,"weight":0.01,"skill":null,"mod_groups":[]}}},"10$":{"Equipment":{"Item":{"name":"10$","notes":"Cash","cost":10.0,"weight":0.01,"skill":null,"mod_groups":[]}}},"1k$ on Account":{"Equipment":{"Item":{"name":"1k$ on Account","notes":null,"cost":1000.0,"weight":0.01,"skill":null,"mod_groups":[]}}},"10$ on Account":{"Equipment":{"Item":{"name":"10$ on Account","notes":null,"cost":10.0,"weight":0.01,"skill":null,"mod_groups":[]}}},"1$":{"Equipment":{"Item":{"name":"1$","notes":"Cash","cost":1.0,"weight":0.01,"skill":null,"mod_groups":[]}}},"1$ on Account":{"Equipment":{"Item":{"name":"1$ on Account","notes":null,"cost":1.0,"weight":0.01,"skill":null,"mod_groups":[]}}},"100$ on Account":{"Equipment":{"Item":{"name":"100$ on Account","notes":null,"cost":100.0,"weight":0.01,"skill":null,"mod_groups":[]}}},"100k$ on Account":{"Equipment":{"Item":{"name":"100k$ on Account","notes":null,"cost":100000.0,"weight":0.01,"skill":null,"mod_groups":[]}}}}},"Weapons: Machine Guns & Autocannons":{"name":"Weapons: Machine Guns & Autocannons","items":{"EX34 Chain Gun 7.62x51mm":{"Equipment":{"Weapon":{"Ranged":{"name":"EX34 Chain Gun 7.62x51mm","damage":[{"Cr":{"Dice":[7,0]}}],"max_damage":null,"acc":15,"ss":20,"rof":{"FullAuto":9},"rcl":-1,"min_range":null,"half_dmg_range":null,"max_range":null,"st_req":null,"tripod":true,"cost":5000.0,"weight":32.0,"skill":null,"notes":null,"shots":{"Box":500},"mod_groups":[],"rl_year":null,"rl_country":null,"tl":null,"lc":null}}}},"NSV 12.7x108mm":{"Equipment":{"Weapon":{"Ranged":{"name":"NSV 12.7x108mm","damage":[{"Cr":{"Dice":[12,0]}}],"max_damage":null,"acc":15,"ss":20,"rof":{"FullAuto":12},"rcl":-1,"min_range":null,"half_dmg_range":null,"max_range":null,"st_req":null,"tripod":true,"cost":6000.0,"weight":120.0,"skill":null,"notes":null,"shots":{"Magazine":50},"mod_groups":[],"rl_year":null,"rl_country":null,"tl":null,"lc":null}}}},"HK21A1 7.62x51mm":{"Equipment":{"Weapon":{"Ranged":{"name":"HK21A1 7.62x51mm","damage":[{"Cr":{"Dice":[7,0]}}],"max_damage":null,"acc":11,"ss":18,"rof":{"FullAuto":15},"rcl":-1,"min_range":null,"half_dmg_range":null,"max_range":null,"st_req":13,"tripod":false,"cost":3000.0,"weight":14.0,"skill":null,"notes":null,"shots":{"Belt":100},"mod_groups":[],"rl_year":null,"rl_country":null,"tl":null,"lc":null}}}},"M134 Minigun 7.62x51mm":{"Equipment":{"Weapon":{"Ranged":{"name":"M134 Minigun 7.62x51mm","damage":[{"Cr":{"Dice":[7,0]}}],"max_damage":null,"acc":15,"ss":20,"rof":{"FullAuto":100},"rcl":-2,"min_range":null,"half_dmg_range":null,"max_range":null,"st_req":null,"tripod":true,"cost":6000.0,"weight":72.0,"skill":null,"notes":null,"shots":{"Magazine":4000},"mod_groups":[],"rl_year":null,"rl_country":null,"tl":null,"lc":null}}}},"M60 7.62x51mm":{"Equipment":{"Weapon":{"Ranged":{"name":"M60 7.62x51mm","damage":[{"Cr":{"Dice":[7,0]}}],"max_damage":null,"acc":10,"ss":19,"rof":{"FullAuto":10},"rcl":-1,"min_range":null,"half_dmg_range":null,"max_range":null,"st_req":13,"tripod":false,"cost":3000.0,"weight":23.0,"skill":null,"notes":null,"shots":{"Belt":100},"mod_groups":[],"rl_year":null,"rl_country":null,"tl":null,"lc":null}}}},"FN Mag. 7.62x51mm":{"Equipment":{"Weapon":{"Ranged":{"name":"FN Mag. 7.62x51mm","damage":[{"Cr":{"Dice":[7,0]}}],"max_damage":null,"acc":10,"ss":19,"rof":{"FullAuto":15},"rcl":-1,"min_range":null,"half_dmg_range":null,"max_range":null,"st_req":13,"tripod":false,"cost":3000.0,"weight":25.0,"skill":null,"notes":null,"shots":{"Belt":100},"mod_groups":[],"rl_year":null,"rl_country":null,"tl":null,"lc":null}}}},"FN Minimi 5.56x45mm":{"Equipment":{"Weapon":{"Ranged":{"name":"FN Minimi 5.56x45mm","damage":[{"Cr":{"Dice":[5,1]}}],"max_damage":null,"acc":10,"ss":15,"rof":{"FullAuto":13},"rcl":-1,"min_range":null,"half_dmg_range":null,"max_range":null,"st_req":12,"tripod":false,"cost":3000.0,"weight":16.0,"skill":null,"notes":null,"shots":{"Belt":200},"mod_groups":[],"rl_year":null,"rl_country":null,"tl":null,"lc":null}}}},"PK 7.62x54mm":{"Equipment":{"Weapon":{"Ranged":{"name":"PK 7.62x54mm","damage":[{"Cr":{"Dice":[7,0]}}],"max_damage":null,"acc":0,"ss":16,"rof":{"FullAuto":12},"rcl":-1,"min_range":null,"half_dmg_range":null,"max_range":null,"st_req":13,"tripod":false,"cost":1400.0,"weight":20.0,"skill":null,"notes":null,"shots":{"Belt":100},"mod_groups":[],"rl_year":null,"rl_country":null,"tl":null,"lc":null}}}},"M214 \"6-pak\" 5.56x45mm":{"Equipment":{"Weapon":{"Ranged":{"name":"M214 \"6-pak\" 5.56x45mm","damage":[{"Cr":{"Dice":[5,1]}}],"max_damage":null,"acc":13,"ss":20,"rof":{"Slow":[66,160]},"rcl":-1,"min_range":null,"half_dmg_range":null,"max_range":null,"st_req":null,"tripod":true,"cost":10000.0,"weight":45.0,"skill":null,"notes":null,"shots":{"Box":500},"mod_groups":[],"rl_year":null,"rl_country":null,"tl":null,"lc":null}}}}}},"Weapons: Sniper Rifles":{"name":"Weapons: Sniper Rifles","items":{"SVD":{"Equipment":{"Weapon":{"Ranged":{"name":"SVD","damage":[{"Cr":{"Dice":[7,2]}}],"max_damage":null,"acc":14,"ss":15,"rof":{"Slow":[1,3]},"rcl":-2,"min_range":null,"half_dmg_range":1300,"max_range":4800,"st_req":11,"tripod":false,"cost":3000.0,"weight":9.0,"skill":null,"notes":null,"shots":{"Magazine":10},"mod_groups":[],"rl_year":null,"rl_country":null,"tl":null,"lc":null}}}},"M40 A1 7.62mm":{"Equipment":{"Item":{"name":"M40 A1 7.62mm","notes":"Acc+16, SS 14, 1/2D 1200, Max 4700, RoF 1/6, Shots 5, ST 12, Rcl -2","cost":4000.0,"weight":12.5,"skill":null,"mod_groups":[]}}},"H&K PSG1 7.62mmN":{"Equipment":{"Weapon":{"Ranged":{"name":"H&K PSG1 7.62mmN","damage":[{"Cr":{"Dice":[7,0]}}],"max_damage":null,"acc":13,"ss":15,"rof":{"Slow":[1,3]},"rcl":-2,"min_range":null,"half_dmg_range":1200,"max_range":4700,"st_req":12,"tripod":false,"cost":4500.0,"weight":16.0,"skill":null,"notes":null,"shots":"Single","mod_groups":[],"rl_year":null,"rl_country":null,"tl":null,"lc":null}}}},"AR15 A2 HBAR 5.56mm":{"Equipment":{"Weapon":{"Ranged":{"name":"AR15 A2 HBAR 5.56mm","damage":[{"Cr":{"Dice":[5,0]}}],"max_damage":null,"acc":13,"ss":13,"rof":{"Trigger":1},"rcl":-2,"min_range":null,"half_dmg_range":700,"max_range":3900,"st_req":11,"tripod":false,"cost":3500.0,"weight":10.0,"skill":null,"notes":null,"shots":{"Magazine":20},"mod_groups":[],"rl_year":null,"rl_country":null,"tl":null,"lc":null}}}},"FR-F2":{"Equipment":{"Weapon":{"Ranged":{"name":"FR-F2","damage":[{"Cr":{"Dice":[7,0]}}],"max_damage":null,"acc":15,"ss":15,"rof":{"Slow":[1,4]},"rcl":-2,"min_range":null,"half_dmg_range":1200,"max_range":4700,"st_req":11,"tripod":false,"cost":4000.0,"weight":11.5,"skill":null,"notes":null,"shots":{"Magazine":10},"mod_groups":[],"rl_year":null,"rl_country":null,"tl":null,"lc":null}}}},"Gail Sniper":{"Equipment":{"Weapon":{"Ranged":{"name":"Gail Sniper","damage":[{"Cr":{"Dice":[7,0]}}],"max_damage":null,"acc":13,"ss":14,"rof":{"Slow":[1,2]},"rcl":-2,"min_range":null,"half_dmg_range":1200,"max_range":4700,"st_req":12,"tripod":false,"cost":3500.0,"weight":15.0,"skill":null,"notes":null,"shots":{"Magazine":20},"mod_groups":[],"rl_year":null,"rl_country":null,"tl":null,"lc":null}}}},"RAI Md 300":{"Equipment":{"Weapon":{"Ranged":{"name":"RAI Md 300","damage":[{"Cr":{"Dice":[7,0]}}],"max_damage":null,"acc":16,"ss":15,"rof":{"Slow":[1,4]},"rcl":-2,"min_range":null,"half_dmg_range":1200,"max_range":4700,"st_req":11,"tripod":false,"cost":4000.0,"weight":12.0,"skill":null,"notes":null,"shots":{"Magazine":5},"mod_groups":[],"rl_year":null,"rl_country":null,"tl":null,"lc":null}}}},"WA 2000":{"Equipment":{"Weapon":{"Ranged":{"name":"WA 2000","damage":[{"Cr":{"Dice":[8,0]}}],"max_damage":null,"acc":16,"ss":13,"rof":{"Slow":[1,3]},"rcl":-2,"min_range":null,"half_dmg_range":1400,"max_range":4900,"st_req":12,"tripod":false,"cost":5000.0,"weight":16.0,"skill":null,"notes":null,"shots":{"Magazine":6},"mod_groups":[],"rl_year":null,"rl_country":null,"tl":null,"lc":null}}}},"RAI Md 500":{"Equipment":{"Weapon":{"Ranged":{"name":"RAI Md 500","damage":[{"Cr":{"Dice":[15,0]}}],"max_damage":null,"acc":10,"ss":19,"rof":{"Slow":[1,10]},"rcl":-4,"min_range":null,"half_dmg_range":2200,"max_range":7400,"st_req":13,"tripod":false,"cost":5500.0,"weight":30.0,"skill":null,"notes":null,"shots":"Single","mod_groups":[],"rl_year":null,"rl_country":null,"tl":null,"lc":null}}}},"Barret M82 .50BMG":{"Equipment":{"Weapon":{"Ranged":{"name":"Barret M82 .50BMG","damage":[{"Cr":{"Dice":[13,0]}}],"max_damage":null,"acc":16,"ss":20,"rof":{"Trigger":2},"rcl":-4,"min_range":null,"half_dmg_range":2200,"max_range":7400,"st_req":13,"tripod":false,"cost":5000.0,"weight":32.0,"skill":null,"notes":null,"shots":{"Magazine":11},"mod_groups":[],"rl_year":null,"rl_country":null,"tl":null,"lc":null}}}}}},"Weapons: Shotguns":{"name":"Weapons: Shotguns","items":{"H&K CAWS 12g semi-auto":{"Equipment":{"Weapon":{"Ranged":{"name":"H&K CAWS 12g semi-auto","damage":[{"Cr":{"Flat":5}}],"max_damage":null,"acc":7,"ss":null,"rof":{"SemiAuto":3},"rcl":-2,"min_range":null,"half_dmg_range":null,"max_range":null,"st_req":12,"tripod":false,"cost":1200.0,"weight":10.0,"skill":"Guns: Shotgun","notes":null,"shots":{"MagazinePlus":[10,1]},"mod_groups":[],"rl_year":null,"rl_country":null,"tl":null,"lc":null}}}},"Striker 12g semi-auto":{"Equipment":{"Weapon":{"Ranged":{"name":"Striker 12g semi-auto","damage":[{"Cr":{"Flat":4}}],"max_damage":null,"acc":5,"ss":null,"rof":{"SemiAuto":3},"rcl":-2,"min_range":null,"half_dmg_range":null,"max_range":null,"st_req":11,"tripod":false,"cost":400.0,"weight":12.0,"skill":"Guns: Shotgun","notes":null,"shots":{"Magazine":12},"mod_groups":[],"rl_year":null,"rl_country":null,"tl":null,"lc":null}}}},"AAI CAWS 12G":{"Equipment":{"Weapon":{"Ranged":{"name":"AAI CAWS 12G","damage":[{"Cr":{"Dice":[3,2]}}],"max_damage":null,"acc":6,"ss":10,"rof":{"FullAuto":8},"rcl":-1,"min_range":null,"half_dmg_range":null,"max_range":null,"st_req":null,"tripod":false,"cost":1200.0,"weight":10.0,"skill":null,"notes":null,"shots":{"Magazine":12},"mod_groups":[],"rl_year":null,"rl_country":"US","tl":7,"lc":null}}}},"Remington-7188 Mk.I 12G":{"Equipment":{"Weapon":{"Ranged":{"name":"Remington-7188 Mk.I 12G","damage":[{"Cr":{"Dice":[4,0]}}],"max_damage":null,"acc":5,"ss":11,"rof":{"FullAuto":7},"rcl":-2,"min_range":null,"half_dmg_range":null,"max_range":null,"st_req":null,"tripod":false,"cost":300.0,"weight":9.0,"skill":null,"notes":null,"shots":{"Magazine":7},"mod_groups":[],"rl_year":null,"rl_country":"US","tl":7,"lc":null}}}},"Ithacha Stakeout 12G":{"Equipment":{"Weapon":{"Ranged":{"name":"Ithacha Stakeout 12G","damage":[{"Cr":{"Dice":[4,0]}}],"max_damage":null,"acc":3,"ss":10,"rof":{"Trigger":3},"rcl":-3,"min_range":null,"half_dmg_range":null,"max_range":null,"st_req":null,"tripod":false,"cost":250.0,"weight":4.0,"skill":null,"notes":null,"shots":{"Magazine":4},"mod_groups":[],"rl_year":null,"rl_country":"IT","tl":7,"lc":null}}}},"SPAS 12 12g semi-auto":{"Equipment":{"Weapon":{"Ranged":{"name":"SPAS 12 12g semi-auto","damage":[{"Cr":{"Flat":4}}],"max_damage":null,"acc":5,"ss":null,"rof":{"SemiAuto":3},"rcl":-2,"min_range":null,"half_dmg_range":null,"max_range":null,"st_req":10,"tripod":false,"cost":400.0,"weight":10.0,"skill":"Guns: Shotgun","notes":null,"shots":{"MagazinePlus":[7,1]},"mod_groups":[],"rl_year":null,"rl_country":null,"tl":null,"lc":null}}}},"Browning Auto-5 12g semi-auto":{"Equipment":{"Weapon":{"Ranged":{"name":"Browning Auto-5 12g semi-auto","damage":[{"Cr":{"Flat":4}}],"max_damage":null,"acc":5,"ss":null,"rof":{"SemiAuto":3},"rcl":-2,"min_range":null,"half_dmg_range":null,"max_range":null,"st_req":11,"tripod":false,"cost":350.0,"weight":8.0,"skill":"Guns: Shotgun","notes":null,"shots":{"MagazinePlus":[5,1]},"mod_groups":[],"rl_year":null,"rl_country":null,"tl":null,"lc":null}}}},"Mossberg 500 12g pump":{"Equipment":{"Weapon":{"Ranged":{"name":"Mossberg 500 12g pump","damage":[{"Cr":{"Flat":4}}],"max_damage":null,"acc":5,"ss":null,"rof":{"SemiAuto":2},"rcl":-3,"min_range":null,"half_dmg_range":null,"max_range":null,"st_req":12,"tripod":false,"cost":200.0,"weight":7.5,"skill":"Guns: Shotgun","notes":null,"shots":{"MagazinePlus":[5,1]},"mod_groups":[],"rl_year":null,"rl_country":null,"tl":null,"lc":null}}}},"Remington 870 12g pump":{"Equipment":{"Weapon":{"Ranged":{"name":"Remington 870 12g pump","damage":[{"Cr":{"Flat":4}}],"max_damage":null,"acc":5,"ss":null,"rof":{"SemiAuto":2},"rcl":-3,"min_range":null,"half_dmg_range":null,"max_range":null,"st_req":12,"tripod":false,"cost":300.0,"weight":8.0,"skill":"Guns: Shotgun","notes":null,"shots":{"MagazinePlus":[5,1]},"mod_groups":[],"rl_year":null,"rl_country":null,"tl":null,"lc":null}}}}}},"Thief/Spy Tools":{"name":"Thief/Spy Tools","items":{"Lockpick Gun (TL7)":{"Equipment":{"Item":{"name":"Lockpick Gun (TL7)","notes":"+2 to skill","cost":50.0,"weight":0.5,"skill":null,"mod_groups":[]}}},"Counterfeit Bill Detector":{"Equipment":{"Item":{"name":"Counterfeit Bill Detector","notes":null,"cost":30.0,"weight":0.5,"skill":null,"mod_groups":[]}}},"Contact Mike Set":{"Equipment":{"Item":{"name":"Contact Mike Set","notes":"+2 to pick mech. locks","cost":300.0,"weight":0.0,"skill":null,"mod_groups":[]}}},"Disguise Kit":{"Equipment":{"Item":{"name":"Disguise Kit","notes":"+2 disguise skill","cost":300.0,"weight":10.0,"skill":null,"mod_groups":[]}}},"Laser Pointer":{"Equipment":{"Item":{"name":"Laser Pointer","notes":null,"cost":50.0,"weight":0.2,"skill":null,"mod_groups":[]}}},"Thermal Lockpick":{"Equipment":{"Item":{"name":"Thermal Lockpick","notes":"Burns off locks","cost":500.0,"weight":1.0,"skill":null,"mod_groups":[]}}},"Lockpicks (TL7)":{"Equipment":{"Item":{"name":"Lockpicks (TL7)","notes":"+1 to skill","cost":20.0,"weight":0.1,"skill":null,"mod_groups":[]}}}}},"Photographic Equipment":{"name":"Photographic Equipment","items":{"Camcorder":{"Equipment":{"Item":{"name":"Camcorder","notes":"A consumer model, with telephoto lens and time/date stamp","cost":900.0,"weight":18.0,"skill":null,"mod_groups":[]}}},"Palmcorder":{"Equipment":{"Item":{"name":"Palmcorder","notes":"A commercially-available video camera, about the size of a cigar box","cost":900.0,"weight":4.0,"skill":null,"mod_groups":[]}}},"Thermographic Film":{"Equipment":{"Item":{"name":"Thermographic Film","notes":"This film produces pictures even in complete darkness, as long as heat sources are present, The prise is pr picture","cost":1.0,"weight":0.0,"skill":null,"mod_groups":[]}}},"Underwater Camera":{"Equipment":{"Item":{"name":"Underwater Camera","notes":null,"cost":500.0,"weight":1.0,"skill":null,"mod_groups":[]}}},"Wescam Camera Mount":{"Equipment":{"Item":{"name":"Wescam Camera Mount","notes":"A gyroscopic stabilizer for all kinds of cameras","cost":10000.0,"weight":50.0,"skill":null,"mod_groups":[]}}},"Lenses: Wide Angel":{"Equipment":{"Item":{"name":"Lenses: Wide Angel","notes":"This lens fit a standard camcorder","cost":70.0,"weight":0.25,"skill":null,"mod_groups":[]}}},"Lenses: Telephoto":{"Equipment":{"Item":{"name":"Lenses: Telephoto","notes":"This lens fit a standard camcorder","cost":300.0,"weight":0.5,"skill":null,"mod_groups":[]}}}}},"Weapons: Electronic/Non-lethal":{"name":"Weapons: Electronic/Non-lethal","items":{"Pepper Spray A":{"Equipment":{"Item":{"name":"Pepper Spray A","notes":"Stun, RoF 1, Shots 5, UV Marker","cost":15.0,"weight":0.5,"skill":null,"mod_groups":[]}}},"Hand Stunner <=150kV":{"Equipment":{"Item":{"name":"Hand Stunner <=150kV","notes":"Stun on HT-5 for 30-HT sec.","cost":80.0,"weight":0.5,"skill":"Knife","mod_groups":[]}}},"Baton Stunner <=200kV":{"Equipment":{"Weapon":{"Melee":{"name":"Baton Stunner <=200kV","damage":[{"Cr":{"Sw":0}},{"Cr":{"Thr":0}}],"max_damage":null,"cost":150.0,"weight":1.0,"skill":"Shortsword","notes":null,"mod_groups":[],"acc":null,"st_req":null}}}},"Hand Stunner <=100kV":{"Equipment":{"Item":{"name":"Hand Stunner <=100kV","notes":"Stun on HT-4 for 25-HT sec.","cost":60.0,"weight":0.5,"skill":"Knife","mod_groups":[]}}},"Hand Stunner <=200kV":{"Equipment":{"Item":{"name":"Hand Stunner <=200kV","notes":"Stun on HT-6 for 35-HT sec.","cost":100.0,"weight":0.5,"skill":"Knife","mod_groups":[]}}},"Hand Stunner <=050kV":{"Equipment":{"Item":{"name":"Hand Stunner <=050kV","notes":"Stun on HT-3 for 20-HT sec.","cost":40.0,"weight":0.5,"skill":"Knife","mod_groups":[]}}},"Air Taser <=050kV":{"Equipment":{"Item":{"name":"Air Taser <=050kV","notes":"SS 14,Acc+2,Stun on HT-3 for 20-HT sec","cost":300.0,"weight":0.5,"skill":"Guns: Taser","mod_groups":[]}}},"Baton Stunner <=150kV":{"Equipment":{"Weapon":{"Melee":{"name":"Baton Stunner <=150kV","damage":[{"Cr":{"Sw":0}},{"Cr":{"Thr":0}}],"max_damage":null,"cost":100.0,"weight":1.0,"skill":"Shortsword","notes":null,"mod_groups":[],"acc":null,"st_req":null}}}},"Pepper Spray B":{"Equipment":{"Item":{"name":"Pepper Spray B","notes":"Stun, Rof 1, Shots 5, Red Dye","cost":15.0,"weight":0.5,"skill":null,"mod_groups":[]}}}}},"Weapon: Knife":{"name":"Weapon: Knife","items":{"Small knife":{"Equipment":{"Weapon":{"Melee":{"name":"Small knife","damage":[{"Cut":{"Sw":-3}},{"Imp":{"Thr":-1}}],"max_damage":null,"cost":30.0,"weight":0.5,"skill":"Knife","notes":null,"mod_groups":[],"acc":0,"st_req":null}}}},"Dagger":{"Equipment":{"Weapon":{"Melee":{"name":"Dagger","damage":[{"Imp":{"Thr":0}}],"max_damage":null,"cost":20.0,"weight":0.5,"skill":"Knife","notes":null,"mod_groups":[],"acc":0,"st_req":null}}}},"Large knife":{"Equipment":{"Weapon":{"Melee":{"name":"Large knife","damage":[{"Cut":{"Sw":-2}},{"Imp":{"Thr":0}}],"max_damage":null,"cost":40.0,"weight":1.0,"skill":"Knife","notes":null,"mod_groups":[],"acc":0,"st_req":null}}}},"Very Large knife":{"Equipment":{"Weapon":{"Melee":{"name":"Very Large knife","damage":[{"Cut":{"Sw":-1}},{"Imp":{"Thr":0}}],"max_damage":null,"cost":60.0,"weight":1.0,"skill":"Knife","notes":null,"mod_groups":[],"acc":0,"st_req":null}}}}}},"Weapons: Hand Grenades (TL 7)":{"name":"Weapons: Hand Grenades (TL 7)","items":{"Grenade/Concussion (TL7)":{"Equipment":{"Weapon":{"Melee":{"name":"Grenade/Concussion (TL7)","damage":[{"Cr":{"Dice":[3,0]}}],"max_damage":null,"cost":25.0,"weight":1.0,"skill":null,"notes":null,"mod_groups":[],"acc":null,"st_req":null}}}},"40mm Grenade/Smoke (TL7)":{"Equipment":{"Item":{"name":"40mm Grenade/Smoke (TL7)","notes":null,"cost":50.0,"weight":0.4,"skill":null,"mod_groups":[]}}},"40mm Grenade/Fragmentation (TL7)":{"Equipment":{"Weapon":{"Melee":{"name":"40mm Grenade/Fragmentation (TL7)","damage":[{"Cr":{"Dice":[2,2]}}],"max_damage":null,"cost":50.0,"weight":0.4,"skill":null,"notes":null,"mod_groups":[],"acc":null,"st_req":null}}}},"Grenade/Fragmentation (TL7)":{"Equipment":{"Weapon":{"Melee":{"name":"Grenade/Fragmentation (TL7)","damage":[{"Cr":{"Dice":[3,0]}}],"max_damage":null,"cost":25.0,"weight":1.0,"skill":null,"notes":null,"mod_groups":[],"acc":null,"st_req":null}}}},"40mm Grenade/Concussion (TL7)":{"Equipment":{"Weapon":{"Melee":{"name":"40mm Grenade/Concussion (TL7)","damage":[{"Cr":{"Dice":[2,2]}}],"max_damage":null,"cost":50.0,"weight":0.4,"skill":null,"notes":null,"mod_groups":[],"acc":null,"st_req":null}}}},"Grenade/Smoke (TL7)":{"Equipment":{"Item":{"name":"Grenade/Smoke (TL7)","notes":null,"cost":25.0,"weight":1.0,"skill":null,"mod_groups":[]}}}}},"Weapon: Staff":{"name":"Weapon: Staff","items":{"Quarterstaff":{"Equipment":{"Weapon":{"Melee":{"name":"Quarterstaff","damage":[{"Cr":{"Sw":2}},{"Cr":{"Thr":2}}],"max_damage":null,"cost":10.0,"weight":4.0,"skill":"Staff","notes":null,"mod_groups":[],"acc":null,"st_req":null}}}}}},"Surveillance Gear":{"name":"Surveillance Gear","items":{"Computer Tap (TEMPEST Gear)":{"Equipment":{"Item":{"name":"Computer Tap (TEMPEST Gear)","notes":"\"Reads\" the radio emissions from monitors","cost":20000.0,"weight":3.0,"skill":null,"mod_groups":[]}}},"Electronic Stethoscope":{"Equipment":{"Item":{"name":"Electronic Stethoscope","notes":"It can hear through one yard of solid material","cost":200.0,"weight":2.0,"skill":null,"mod_groups":[]}}},"Long-Ranged Microphone":{"Equipment":{"Item":{"name":"Long-Ranged Microphone","notes":"A microphone with a parabolic dish to concentrate sound, Can hear wishpered speach at 100 yards","cost":450.0,"weight":2.0,"skill":null,"mod_groups":[]}}},"Radio Scanner":{"Equipment":{"Item":{"name":"Radio Scanner","notes":"This radio rapidly searches all possible frequencies for communications","cost":150.0,"weight":2.0,"skill":null,"mod_groups":[]}}},"Fiber-Optic Scope":{"Equipment":{"Item":{"name":"Fiber-Optic Scope","notes":"This is just the cable that you can attatch to a camera, cost is pr foot","cost":100.0,"weight":0.0,"skill":null,"mod_groups":[]}}},"Laser Microphone":{"Equipment":{"Item":{"name":"Laser Microphone","notes":"Turns any window into a bug. It picks up the glas-vibrations caused by speach, rng 50 yards","cost":5000.0,"weight":2.0,"skill":null,"mod_groups":[]}}},"Oscilloscope":{"Equipment":{"Item":{"name":"Oscilloscope","notes":"Combined with a standard telephone bug, this instrument can record any number the target dials","cost":1000.0,"weight":5.0,"skill":null,"mod_groups":[]}}},"Micro-Camera":{"Equipment":{"Item":{"name":"Micro-Camera","notes":"The size is 2\" long and 1\" wide, with a 24-exposure roll of film","cost":1500.0,"weight":0.0,"skill":null,"mod_groups":[]}}}}},"Weapons: Grenade Launchers":{"name":"Weapons: Grenade Launchers","items":{"Mk19 AGL 40x53mm":{"Equipment":{"Weapon":{"Ranged":{"name":"Mk19 AGL 40x53mm","damage":[{"Cr":{"Dice":[3,0]}},{"Imp":{"Dice":[3,0]}}],"max_damage":null,"acc":15,"ss":null,"rof":{"FullAuto":6},"rcl":-1,"min_range":null,"half_dmg_range":null,"max_range":null,"st_req":null,"tripod":true,"cost":6000.0,"weight":76.0,"skill":null,"notes":null,"shots":{"Belt":2147483647},"mod_groups":[],"rl_year":null,"rl_country":null,"tl":null,"lc":null}}}},"M203 40x46mm":{"Equipment":{"Weapon":{"Ranged":{"name":"M203 40x46mm","damage":[{"Cr":{"Dice":[2,2]}},{"Imp":{"Dice":[3,0]}}],"max_damage":null,"acc":6,"ss":null,"rof":{"Slow":[1,4]},"rcl":-1,"min_range":null,"half_dmg_range":null,"max_range":null,"st_req":11,"tripod":false,"cost":500.0,"weight":4.0,"skill":null,"notes":null,"shots":"Single","mod_groups":[],"rl_year":null,"rl_country":null,"tl":null,"lc":null}}}},"M79 40x46mm":{"Equipment":{"Weapon":{"Ranged":{"name":"M79 40x46mm","damage":[{"Cr":{"Dice":[2,0]}},{"Imp":{"Dice":[3,0]}}],"max_damage":null,"acc":6,"ss":12,"rof":{"Slow":[1,4]},"rcl":-2,"min_range":null,"half_dmg_range":null,"max_range":null,"st_req":12,"tripod":false,"cost":250.0,"weight":7.0,"skill":null,"notes":null,"shots":"Single","mod_groups":[],"rl_year":null,"rl_country":null,"tl":null,"lc":null}}}}}},"Life Support Equipment":{"name":"Life Support Equipment","items":{"NBC suit anti-corrosive":{"Equipment":{"Item":{"name":"NBC suit anti-corrosive","notes":null,"cost":200.0,"weight":0.0,"skill":null,"mod_groups":[]}}},"NBC suit PF2 anti-radiation":{"Equipment":{"Item":{"name":"NBC suit PF2 anti-radiation","notes":null,"cost":200.0,"weight":0.0,"skill":null,"mod_groups":[]}}},"Vacc Suit H20/Food System":{"Equipment":{"Item":{"name":"Vacc Suit H20/Food System","notes":null,"cost":500.0,"weight":0.0,"skill":null,"mod_groups":[]}}},"Vacc Suit Waste Relief System":{"Equipment":{"Item":{"name":"Vacc Suit Waste Relief System","notes":null,"cost":500.0,"weight":0.0,"skill":null,"mod_groups":[]}}},"Vacc Suit PF2 anti-radiation":{"Equipment":{"Item":{"name":"Vacc Suit PF2 anti-radiation","notes":null,"cost":200.0,"weight":0.0,"skill":null,"mod_groups":[]}}},"Magnetized Boot Plates":{"Equipment":{"Item":{"name":"Magnetized Boot Plates","notes":null,"cost":100.0,"weight":2.0,"skill":null,"mod_groups":[]}}},"Air Mask: cheap":{"Equipment":{"Item":{"name":"Air Mask: cheap","notes":null,"cost":20.0,"weight":1.5,"skill":null,"mod_groups":[]}}},"Vacc Suit Extra Repair Patches":{"Equipment":{"Item":{"name":"Vacc Suit Extra Repair Patches","notes":null,"cost":10.0,"weight":0.0,"skill":null,"mod_groups":[]}}},"NBC suit PF5 anti-radiation":{"Equipment":{"Item":{"name":"NBC suit PF5 anti-radiation","notes":null,"cost":1000.0,"weight":0.0,"skill":null,"mod_groups":[]}}},"Vacc Suit PF10 anti-radiation":{"Equipment":{"Item":{"name":"Vacc Suit PF10 anti-radiation","notes":null,"cost":2000.0,"weight":40.0,"skill":null,"mod_groups":[]}}},"Vacc Suit":{"Equipment":{"Armor":{"name":"Vacc Suit","dr":{"All":1},"pd":{"All":0},"cover":[],"cost":1000.0,"weight":10.0,"mod_groups":[],"skill":null,"stats_affected":[],"skills_affected":[],"container":null,"_extra":[]}}},"Vacc Suit Reflective Coating":{"Equipment":{"Item":{"name":"Vacc Suit Reflective Coating","notes":"Reflec armor, PF2 vs. rad.","cost":300.0,"weight":0.0,"skill":null,"mod_groups":[]}}},"NBC suit air mask":{"Equipment":{"Item":{"name":"NBC suit air mask","notes":null,"cost":100.0,"weight":0.0,"skill":null,"mod_groups":[]}}},"Hand Thruster":{"Equipment":{"Item":{"name":"Hand Thruster","notes":null,"cost":50.0,"weight":4.0,"skill":null,"mod_groups":[]}}},"Thruster Pack":{"Equipment":{"Item":{"name":"Thruster Pack","notes":null,"cost":2000.0,"weight":45.0,"skill":null,"mod_groups":[]}}},"Filter attachment":{"Equipment":{"Item":{"name":"Filter attachment","notes":null,"cost":100.0,"weight":1.0,"skill":null,"mod_groups":[]}}},"NBC suit":{"Equipment":{"Armor":{"name":"NBC suit","dr":{"All":1},"pd":{"All":0},"cover":[3,18],"cost":600.0,"weight":10.0,"mod_groups":[],"skill":null,"stats_affected":[],"skills_affected":[],"container":null,"_extra":[]}}},"Vacc Suit Helmet Light":{"Equipment":{"Item":{"name":"Vacc Suit Helmet Light","notes":null,"cost":30.0,"weight":0.0,"skill":null,"mod_groups":[]}}},"Vacc Suit PF5 anti-radiation":{"Equipment":{"Item":{"name":"Vacc Suit PF5 anti-radiation","notes":null,"cost":1000.0,"weight":20.0,"skill":null,"mod_groups":[]}}},"Air Tank (TL7)":{"Equipment":{"Item":{"name":"Air Tank (TL7)","notes":"1 hour","cost":100.0,"weight":30.0,"skill":null,"mod_groups":[]}}},"Wet Suit":{"Equipment":{"Armor":{"name":"Wet Suit","dr":{"All":1},"pd":{"All":0},"cover":[],"cost":500.0,"weight":20.0,"mod_groups":[],"skill":null,"stats_affected":[],"skills_affected":[],"container":null,"_extra":[]}}},"Scrubber":{"Equipment":{"Item":{"name":"Scrubber","notes":"2x tank life","cost":200.0,"weight":1.0,"skill":null,"mod_groups":[]}}}}},"Weapons: Anti-Tank Weapons":{"name":"Weapons: Anti-Tank Weapons","items":{"TOW (ATGM)":{"Equipment":{"Weapon":{"Ranged":{"name":"TOW (ATGM)","damage":[{"Cr":{"Dice":[56,0]}}],"max_damage":null,"acc":14,"ss":20,"rof":{"Slow":[1,7]},"rcl":null,"min_range":65,"half_dmg_range":null,"max_range":3000,"st_req":null,"tripod":false,"cost":40000.0,"weight":260.0,"skill":null,"notes":null,"shots":"Single","mod_groups":[],"rl_year":null,"rl_country":null,"tl":null,"lc":null}}}},"RPG-2 82mm(LAW)":{"Equipment":{"Weapon":{"Ranged":{"name":"RPG-2 82mm(LAW)","damage":[{"Cr":{"Dice":[18,0]}}],"max_damage":null,"acc":9,"ss":15,"rof":{"Slow":[1,5]},"rcl":null,"min_range":10,"half_dmg_range":100,"max_range":150,"st_req":null,"tripod":false,"cost":200.0,"weight":6.0,"skill":null,"notes":null,"shots":"Single","mod_groups":[],"rl_year":null,"rl_country":null,"tl":null,"lc":null}}}},"M72 66mm (LAW)":{"Equipment":{"Weapon":{"Ranged":{"name":"M72 66mm (LAW)","damage":[{"Cr":{"Dice":[24,0]}}],"max_damage":null,"acc":9,"ss":14,"rof":{"Trigger":1},"rcl":null,"min_range":8,"half_dmg_range":200,"max_range":300,"st_req":null,"tripod":false,"cost":250.0,"weight":5.0,"skill":null,"notes":null,"shots":"Single","mod_groups":[],"rl_year":null,"rl_country":null,"tl":null,"lc":null}}}},"RPG-7 85mm(LAW)":{"Equipment":{"Weapon":{"Ranged":{"name":"RPG-7 85mm(LAW)","damage":[{"Cr":{"Dice":[30,0]}}],"max_damage":null,"acc":10,"ss":16,"rof":{"Slow":[1,5]},"rcl":null,"min_range":11,"half_dmg_range":400,"max_range":500,"st_req":null,"tripod":false,"cost":400.0,"weight":20.0,"skill":null,"notes":null,"shots":"Single","mod_groups":[],"rl_year":null,"rl_country":null,"tl":null,"lc":null}}}},"Milan (ATGM)":{"Equipment":{"Weapon":{"Ranged":{"name":"Milan (ATGM)","damage":[{"Cr":{"Dice":[48,0]}}],"max_damage":null,"acc":14,"ss":20,"rof":{"Slow":[1,7]},"rcl":null,"min_range":25,"half_dmg_range":null,"max_range":2000,"st_req":null,"tripod":false,"cost":30000.0,"weight":57.0,"skill":null,"notes":null,"shots":"Single","mod_groups":[],"rl_year":null,"rl_country":null,"tl":null,"lc":null}}}},"M47 Dragon(ATGM)":{"Equipment":{"Weapon":{"Ranged":{"name":"M47 Dragon(ATGM)","damage":[{"Cr":{"Dice":[48,0]}}],"max_damage":null,"acc":15,"ss":15,"rof":{"Slow":[1,6]},"rcl":null,"min_range":65,"half_dmg_range":null,"max_range":1000,"st_req":null,"tripod":false,"cost":10000.0,"weight":31.0,"skill":null,"notes":null,"shots":"Single","mod_groups":[],"rl_year":null,"rl_country":null,"tl":null,"lc":null}}}},"Carl Gustav 84mm(LAW)":{"Equipment":{"Item":{"name":"Carl Gustav 84mm(LAW)","notes":"Acc+10, SS 17, Min 12, 1/2D 400, Max 1000, RoF 1/5, Shots 1","cost":3000.0,"weight":31.0,"skill":null,"mod_groups":[]}}},"AT-3 Sagger (ATGM)":{"Equipment":{"Weapon":{"Ranged":{"name":"AT-3 Sagger (ATGM)","damage":[{"Cr":{"Dice":[48,0]}}],"max_damage":null,"acc":14,"ss":23,"rof":{"Slow":[1,10]},"rcl":null,"min_range":300,"half_dmg_range":null,"max_range":3000,"st_req":null,"tripod":false,"cost":20000.0,"weight":260.0,"skill":null,"notes":null,"shots":"Single","mod_groups":[],"rl_year":null,"rl_country":null,"tl":null,"lc":null}}}}}},"Weapon Accessories":{"name":"Weapon Accessories","items":{"Holster: Concealed":{"Equipment":{"Item":{"name":"Holster: Concealed","notes":null,"cost":30.0,"weight":0.5,"skill":null,"mod_groups":[]}}},"Telescopic Sight: 4X30mm":{"Equipment":{"Item":{"name":"Telescopic Sight: 4X30mm","notes":"Acc+2","cost":60.0,"weight":0.5,"skill":null,"mod_groups":[]}}},"Telescopic Sight: 2-8X40mm":{"Equipment":{"Item":{"name":"Telescopic Sight: 2-8X40mm","notes":"Acc(+1/+4)","cost":120.0,"weight":0.5,"skill":null,"mod_groups":[]}}},"Holster: Web belt":{"Equipment":{"Item":{"name":"Holster: Web belt","notes":null,"cost":25.0,"weight":0.5,"skill":null,"mod_groups":[]}}},"Glock Compensator":{"Equipment":{"Item":{"name":"Glock Compensator","notes":"improves Rcl by 1","cost":300.0,"weight":0.0,"skill":null,"mod_groups":[]}}},"Laser Sight":{"Equipment":{"Item":{"name":"Laser Sight","notes":"SS*.5, Acc+2","cost":250.0,"weight":0.2,"skill":null,"mod_groups":[]}}},"Telescopic Sight: 8-40X60mm":{"Equipment":{"Item":{"name":"Telescopic Sight: 8-40X60mm","notes":"Acc(+4/+20), must be braced","cost":500.0,"weight":1.5,"skill":null,"mod_groups":[]}}},"Taser Laser Sight":{"Equipment":{"Item":{"name":"Taser Laser Sight","notes":"SS*0.5, Acc+2","cost":150.0,"weight":0.2,"skill":null,"mod_groups":[]}}},"Glock Laser Sight":{"Equipment":{"Item":{"name":"Glock Laser Sight","notes":"SS*.5, Acc+2","cost":450.0,"weight":0.0,"skill":null,"mod_groups":[]}}},"IR/Light Inten Rifle Scope: 4X30mm":{"Equipment":{"Item":{"name":"IR/Light Inten Rifle Scope: 4X30mm","notes":"Acc+2","cost":600.0,"weight":2.5,"skill":null,"mod_groups":[]}}},"Aimpoint":{"Equipment":{"Item":{"name":"Aimpoint","notes":"SS*.5, Acc+1","cost":100.0,"weight":0.1,"skill":null,"mod_groups":[]}}},"Holster: Shoulder":{"Equipment":{"Item":{"name":"Holster: Shoulder","notes":null,"cost":30.0,"weight":0.5,"skill":null,"mod_groups":[]}}},"Tactical Vest":{"Equipment":{"Item":{"name":"Tactical Vest","notes":"Mesh w/pouches, holster & backpack","cost":85.0,"weight":2.0,"skill":null,"mod_groups":[]}}},"Silencer":{"Equipment":{"Item":{"name":"Silencer","notes":"No damage modifier","cost":100.0,"weight":0.3,"skill":null,"mod_groups":[]}}},"Holster: Belt pack":{"Equipment":{"Item":{"name":"Holster: Belt pack","notes":null,"cost":35.0,"weight":0.5,"skill":null,"mod_groups":[]}}}}},"False Id & Documents":{"name":"False Id & Documents","items":{"Passports":{"Equipment":{"Item":{"name":"Passports","notes":null,"cost":200.0,"weight":0.0,"skill":null,"mod_groups":[]}}},"Death Certificate":{"Equipment":{"Item":{"name":"Death Certificate","notes":null,"cost":500.0,"weight":0.0,"skill":null,"mod_groups":[]}}},"Boating License":{"Equipment":{"Item":{"name":"Boating License","notes":null,"cost":100.0,"weight":0.0,"skill":null,"mod_groups":[]}}},"Marriage License":{"Equipment":{"Item":{"name":"Marriage License","notes":null,"cost":100.0,"weight":0.0,"skill":null,"mod_groups":[]}}},"Weapons Permit":{"Equipment":{"Item":{"name":"Weapons Permit","notes":null,"cost":250.0,"weight":0.0,"skill":null,"mod_groups":[]}}},"Pilot's License":{"Equipment":{"Item":{"name":"Pilot's License","notes":null,"cost":500.0,"weight":0.0,"skill":null,"mod_groups":[]}}},"Military ID":{"Equipment":{"Item":{"name":"Military ID","notes":"A simple photo ID","cost":250.0,"weight":0.0,"skill":null,"mod_groups":[]}}},"Professional License":{"Equipment":{"Item":{"name":"Professional License","notes":null,"cost":300.0,"weight":0.0,"skill":null,"mod_groups":[]}}},"Visa":{"Equipment":{"Item":{"name":"Visa","notes":"Not the credit card type","cost":500.0,"weight":0.0,"skill":null,"mod_groups":[]}}},"Vehicular Registration":{"Equipment":{"Item":{"name":"Vehicular Registration","notes":null,"cost":50.0,"weight":0.0,"skill":null,"mod_groups":[]}}},"Driver's License":{"Equipment":{"Item":{"name":"Driver's License","notes":null,"cost":25.0,"weight":0.0,"skill":null,"mod_groups":[]}}},"Birth Certificates":{"Equipment":{"Item":{"name":"Birth Certificates","notes":null,"cost":50.0,"weight":0.0,"skill":null,"mod_groups":[]}}}}},"Weapons: Flamethrowers":{"name":"Weapons: Flamethrowers","items":{"LPO-50":{"Equipment":{"Weapon":{"Ranged":{"name":"LPO-50","damage":[{"Cr":{"Dice":[3,0]}}],"max_damage":null,"acc":7,"ss":null,"rof":{"Trigger":1},"rcl":-3,"min_range":null,"half_dmg_range":null,"max_range":70,"st_req":null,"tripod":false,"cost":150.0,"weight":52.0,"skill":null,"notes":null,"shots":{"Flamethrowerlike":[3,9]},"mod_groups":[],"rl_year":null,"rl_country":null,"tl":null,"lc":null}}}}}},"Weapon: Shortsword":{"name":"Weapon: Shortsword","items":{"Baton":{"Equipment":{"Weapon":{"Melee":{"name":"Baton","damage":[{"Cr":{"Sw":0}},{"Cr":{"Thr":0}}],"max_damage":null,"cost":20.0,"weight":1.0,"skill":"Shortsword","notes":null,"mod_groups":[],"acc":null,"st_req":null}}}},"Collapsable Baton":{"Equipment":{"Item":{"name":"Collapsable Baton","notes":"Cr/Sw","cost":40.0,"weight":1.0,"skill":"Shortsword","mod_groups":[]}}},"Shillelagh":{"Equipment":{"Weapon":{"Melee":{"name":"Shillelagh","damage":[{"Cr":{"Sw":0}},{"Cr":{"Thr":0}}],"max_damage":null,"cost":0.0,"weight":1.0,"skill":"Shortsword","notes":null,"mod_groups":[],"acc":null,"st_req":null}}}},"Machete":{"Equipment":{"Weapon":{"Melee":{"name":"Machete","damage":[{"Cut":{"Sw":1}},{"Imp":{"Thr":-1}}],"max_damage":null,"cost":20.0,"weight":2.0,"skill":"Shortsword","notes":null,"mod_groups":[],"acc":null,"st_req":null}}}}}},"Weapons: Rifles":{"name":"Weapons: Rifles","items":{"H&K G11":{"Equipment":{"Weapon":{"Ranged":{"name":"H&K G11","damage":[{"Cr":{"Dice":[4,0]}},{"Spec":"Var"}],"max_damage":null,"acc":12,"ss":12,"rof":null,"rcl":-1,"min_range":null,"half_dmg_range":null,"max_range":null,"st_req":10,"tripod":false,"cost":5000.0,"weight":8.0,"skill":null,"notes":null,"shots":{"Magazine":50},"mod_groups":[],"rl_year":null,"rl_country":null,"tl":null,"lc":null}}}},"M14 7.62X51mm":{"Equipment":{"Weapon":{"Ranged":{"name":"M14 7.62X51mm","damage":[{"Cr":{"Flat":7}}],"max_damage":null,"acc":10,"ss":null,"rof":{"FullAuto":10},"rcl":-2,"min_range":null,"half_dmg_range":null,"max_range":null,"st_req":11,"tripod":false,"cost":400.0,"weight":11.0,"skill":"Guns: Light Automatic","notes":null,"shots":{"MagazinePlus":[20,1]},"mod_groups":[],"rl_year":null,"rl_country":null,"tl":null,"lc":null}}}},"L85A1 5.56x45mm":{"Equipment":{"Weapon":{"Ranged":{"name":"L85A1 5.56x45mm","damage":[{"Cr":{"Dice":[5,0]}}],"max_damage":null,"acc":10,"ss":11,"rof":{"FullAuto":12},"rcl":-1,"min_range":null,"half_dmg_range":null,"max_range":null,"st_req":10,"tripod":false,"cost":500.0,"weight":10.0,"skill":null,"notes":null,"shots":{"Magazine":20},"mod_groups":[],"rl_year":null,"rl_country":null,"tl":null,"lc":null}}}},"M16 5.56X45mm":{"Equipment":{"Weapon":{"Ranged":{"name":"M16 5.56X45mm","damage":[{"Cr":{"Flat":5}}],"max_damage":null,"acc":11,"ss":null,"rof":{"FullAuto":12},"rcl":-1,"min_range":null,"half_dmg_range":null,"max_range":null,"st_req":9,"tripod":false,"cost":550.0,"weight":8.0,"skill":"Guns: Light Automatic","notes":null,"shots":{"MagazinePlus":[30,1]},"mod_groups":[],"rl_year":null,"rl_country":null,"tl":null,"lc":null}}}},"FA-MAS 5.56x45mm":{"Equipment":{"Weapon":{"Ranged":{"name":"FA-MAS 5.56x45mm","damage":[{"Cr":{"Dice":[5,0]}}],"max_damage":null,"acc":10,"ss":11,"rof":{"FullAuto":16},"rcl":-1,"min_range":null,"half_dmg_range":null,"max_range":null,"st_req":9,"tripod":false,"cost":500.0,"weight":8.5,"skill":null,"notes":null,"shots":{"Magazine":25},"mod_groups":[],"rl_year":null,"rl_country":null,"tl":null,"lc":null}}}},"H&K HK53 5.56x51mm":{"Equipment":{"Weapon":{"Ranged":{"name":"H&K HK53 5.56x51mm","damage":[{"Cr":{"Dice":[5,0]}}],"max_damage":null,"acc":9,"ss":10,"rof":{"FullAuto":11},"rcl":-2,"min_range":null,"half_dmg_range":null,"max_range":null,"st_req":10,"tripod":false,"cost":500.0,"weight":7.0,"skill":null,"notes":null,"shots":{"Magazine":25},"mod_groups":[],"rl_year":null,"rl_country":null,"tl":null,"lc":null}}}},"AKM ":{"Equipment":{"Weapon":{"Ranged":{"name":"AKM","damage":[{"Cr":{"Dice":[7,0]}}],"max_damage":null,"acc":7,"ss":12,"rof":{"FullAuto":10},"rcl":-2,"min_range":null,"half_dmg_range":null,"max_range":null,"st_req":9,"tripod":false,"cost":300.0,"weight":9.0,"skill":null,"notes":null,"shots":{"Magazine":30},"mod_groups":[],"rl_year":null,"rl_country":null,"tl":null,"lc":null}}}},"FN-FAL 7.62x51mm":{"Equipment":{"Weapon":{"Ranged":{"name":"FN-FAL 7.62x51mm","damage":[{"Cr":{"Dice":[7,0]}}],"max_damage":null,"acc":11,"ss":null,"rof":{"FullAuto":11},"rcl":-2,"min_range":null,"half_dmg_range":null,"max_range":null,"st_req":11,"tripod":false,"cost":900.0,"weight":11.0,"skill":null,"notes":null,"shots":{"Magazine":20},"mod_groups":[],"rl_year":null,"rl_country":null,"tl":null,"lc":null}}}},"AK-74 ":{"Equipment":{"Weapon":{"Ranged":{"name":"AK-74","damage":[{"Cr":{"Dice":[5,0]}}],"max_damage":null,"acc":10,"ss":12,"rof":{"FullAuto":12},"rcl":-1,"min_range":null,"half_dmg_range":null,"max_range":null,"st_req":9,"tripod":false,"cost":300.0,"weight":8.0,"skill":null,"notes":null,"shots":{"Magazine":30},"mod_groups":[],"rl_year":null,"rl_country":null,"tl":null,"lc":null}}}},"Gail 5.56x45mm":{"Equipment":{"Weapon":{"Ranged":{"name":"Gail 5.56x45mm","damage":[{"Cr":{"Dice":[5,0]}}],"max_damage":null,"acc":10,"ss":11,"rof":{"FullAuto":12},"rcl":-1,"min_range":null,"half_dmg_range":null,"max_range":null,"st_req":9,"tripod":false,"cost":648.0,"weight":10.0,"skill":null,"notes":null,"shots":{"Magazine":35},"mod_groups":[],"rl_year":null,"rl_country":null,"tl":null,"lc":null}}}},"AK-47 7.62X39mm":{"Equipment":{"Weapon":{"Ranged":{"name":"AK-47 7.62X39mm","damage":[{"Cr":{"Dice":[5,1]}}],"max_damage":null,"acc":7,"ss":null,"rof":{"FullAuto":10},"rcl":-1,"min_range":null,"half_dmg_range":null,"max_range":null,"st_req":10,"tripod":false,"cost":300.0,"weight":10.0,"skill":"Guns: Light Automatic","notes":null,"shots":{"MagazinePlus":[30,1]},"mod_groups":[],"rl_year":null,"rl_country":null,"tl":null,"lc":null}}}},"AUG 5.56x45mm":{"Equipment":{"Weapon":{"Ranged":{"name":"AUG 5.56x45mm","damage":[{"Cr":{"Dice":[5,0]}}],"max_damage":null,"acc":10,"ss":11,"rof":{"FullAuto":11},"rcl":-1,"min_range":null,"half_dmg_range":null,"max_range":null,"st_req":9,"tripod":false,"cost":540.0,"weight":9.0,"skill":null,"notes":null,"shots":{"Magazine":30},"mod_groups":[],"rl_year":null,"rl_country":null,"tl":null,"lc":null}}}},"Remington 742 .30-06 semi-auto":{"Equipment":{"Weapon":{"Ranged":{"name":"Remington 742 .30-06 semi-auto","damage":[{"Cr":{"Dice":[7,1]}}],"max_damage":null,"acc":11,"ss":null,"rof":{"SemiAuto":3},"rcl":-2,"min_range":null,"half_dmg_range":null,"max_range":null,"st_req":11,"tripod":false,"cost":700.0,"weight":10.0,"skill":"Guns: Rifle","notes":null,"shots":{"MagazinePlus":[10,1]},"mod_groups":[],"rl_year":null,"rl_country":null,"tl":null,"lc":null}}}},"H&K G3 7.62x51mm":{"Equipment":{"Weapon":{"Ranged":{"name":"H&K G3 7.62x51mm","damage":[{"Cr":{"Dice":[7,0]}}],"max_damage":null,"acc":10,"ss":11,"rof":{"FullAuto":10},"rcl":-2,"min_range":null,"half_dmg_range":null,"max_range":null,"st_req":11,"tripod":false,"cost":550.0,"weight":11.0,"skill":null,"notes":null,"shots":{"Magazine":20},"mod_groups":[],"rl_year":null,"rl_country":null,"tl":null,"lc":null}}}}}},"Sensor Equipment":{"name":"Sensor Equipment","items":{"IR sensor: pocket":{"Equipment":{"Item":{"name":"IR sensor: pocket","notes":"10 yds(cluttered)/100 yds(open)","cost":100.0,"weight":0.5,"skill":null,"mod_groups":[]}}},"IR/Light Inten Scope":{"Equipment":{"Item":{"name":"IR/Light Inten Scope","notes":null,"cost":400.0,"weight":2.0,"skill":null,"mod_groups":[]}}},"Anti-glare Goggles":{"Equipment":{"Item":{"name":"Anti-glare Goggles","notes":null,"cost":150.0,"weight":0.5,"skill":null,"mod_groups":[]}}},"IR sensor: hand held":{"Equipment":{"Item":{"name":"IR sensor: hand held","notes":"150 yds(cluttered)/1000 yds(open)","cost":200.0,"weight":1.0,"skill":null,"mod_groups":[]}}},"IR/Light Inten Goggles":{"Equipment":{"Armor":{"name":"IR/Light Inten Goggles","dr":{"All":4},"pd":{"All":2},"cover":[5],"cost":1000.0,"weight":2.0,"mod_groups":[],"skill":null,"stats_affected":[],"skills_affected":[],"container":null,"_extra":[]}}}}},"Misc Equipment":{"name":"Misc Equipment","items":{"Linethrowing Rocket":{"Equipment":{"Item":{"name":"Linethrowing Rocket","notes":"This rocket can carry a rope 250 yards","cost":200.0,"weight":10.0,"skill":null,"mod_groups":[]}}},"Airfoil Parachute":{"Equipment":{"Item":{"name":"Airfoil Parachute","notes":"Necessary for HAHO an HALO parachuting, glides at 30 mph","cost":1000.0,"weight":50.0,"skill":null,"mod_groups":[]}}},"Grapnel Launcher":{"Equipment":{"Item":{"name":"Grapnel Launcher","notes":"This air-powered launcer fires a grapnel and rope 75 yards","cost":500.0,"weight":15.0,"skill":null,"mod_groups":[]}}}}}}}}
